devansh1/__init__.py
devansh1/example.py
devansh1-0.0.2.dist-info/LICENSE
devansh1-0.0.2.dist-info/METADATA
devansh1-0.0.2.dist-info/WHEEL
devansh1-0.0.2.dist-info/top_level.txt
devansh1-0.0.2.dist-info/RECORD
