Metadata-Version: 2.1
Name: devansh1
Version: 0.0.2
Summary: various projetcs
Author: DevanshMistry
Author-email: <devanshmistry890@gmail.com>
License: UNKNOWN
Keywords: python,devansh,flask
Platform: UNKNOWN
Classifier: Development Status :: 1 - Planning
Classifier: Intended Audience :: Developers
Classifier: Programming Language :: Python :: 3
Classifier: Operating System :: Unix
Classifier: Operating System :: MacOS
Classifier: Operating System :: Microsoft :: Windows
License-File: LICENSE
Requires-Dist: Flask
Requires-Dist: numpy
Requires-Dist: pandas
Requires-Dist: scikit-learn
